intutils/__init__.py
intutils-3.1.0.dist-info/LICENSE
intutils-3.1.0.dist-info/METADATA
intutils-3.1.0.dist-info/WHEEL
intutils-3.1.0.dist-info/top_level.txt
intutils-3.1.0.dist-info/RECORD
