Metadata-Version: 2.1
Name: intutils
Version: 3.1.0
Summary: Basic integer manipulation library.
Home-page: https://github.com/rdilweb/intutils
Author: Reece Dunham
Author-email: me@rdil.rocks
License: MIT
Project-URL: Documentation, https://docs.rdil.rocks/libraries/intutils/
Keywords: int,integer,utils,util,utilities
Platform: UNKNOWN
Requires-Python: >3.3
